Metadata-Version: 2.4
Name: swe-ai-agent
Version: 2.1.7
Summary: Headless Agentic IDE with reasoning mode and in built Browser
Home-page: https://github.com/sweagent/swe-agent
Author: SWE Agent Team
Author-email: Harish Santhanalakshmi Ganesan <harishsg99@gmail.com>
Maintainer-email: Harish Santhanalakshmi Ganesan <harishsg99@gmail.com>
License: MIT
Project-URL: Homepage, https://sweagent.dev
Project-URL: Repository, https://github.com/sweagent/swe-agent
Project-URL: Documentation, https://docs.sweagent.dev
Project-URL: Bug Tracker, https://github.com/sweagent/swe-agent/issues
Keywords: ai,agent,code,software-engineering,reinforcement-learning,o1-reasoning,iterative-improvement,langraph,claude,anthropic,openrouter,multi-provider,gpt-4o,llama,ai-models,ide,headless,automation,development,programming-assistant
Classifier: Development Status :: 4 - Beta
Classifier: Intended Audience :: Developers
Classifier: License :: OSI Approved :: MIT License
Classifier: Operating System :: OS Independent
Classifier: Programming Language :: Python :: 3
Classifier: Programming Language :: Python :: 3.8
Classifier: Programming Language :: Python :: 3.9
Classifier: Programming Language :: Python :: 3.10
Classifier: Programming Language :: Python :: 3.11
Classifier: Programming Language :: Python :: 3.12
Classifier: Topic :: Software Development :: Libraries :: Python Modules
Classifier: Topic :: Software Development :: Code Generators
Classifier: Topic :: Scientific/Engineering :: Artificial Intelligence
Classifier: Topic :: Utilities
Requires-Python: >=3.8
License-File: LICENSE
Requires-Dist: anthropic>=0.40.0
Requires-Dist: langgraph>=0.2.35
Requires-Dist: langchain>=0.3.7
Requires-Dist: langchain-anthropic>=0.2.4
Requires-Dist: langchain-core>=0.3.15
Requires-Dist: langchain-mcp-adapters>=0.1.0
Requires-Dist: rich>=13.0.0
Requires-Dist: click>=8.0.0
Requires-Dist: psutil>=5.9.0
Requires-Dist: pydantic>=2.0.0
Requires-Dist: python-dotenv>=1.0.0
Requires-Dist: requests>=2.31.0
Requires-Dist: aiohttp>=3.9.0
Requires-Dist: beautifulsoup4>=4.12.0
Requires-Dist: trafilatura>=1.12.0
Requires-Dist: tavily-python>=0.5.0
Requires-Dist: detect-secrets>=1.5.0
Requires-Dist: setuptools>=65.0.0
Requires-Dist: typing-extensions>=4.8.0
Provides-Extra: dev
Requires-Dist: pytest>=6.0; extra == "dev"
Requires-Dist: pytest-asyncio; extra == "dev"
Requires-Dist: black; extra == "dev"
Requires-Dist: flake8; extra == "dev"
Requires-Dist: mypy; extra == "dev"
Requires-Dist: twine; extra == "dev"
Requires-Dist: build; extra == "dev"
Provides-Extra: docs
Requires-Dist: sphinx; extra == "docs"
Requires-Dist: sphinx-rtd-theme; extra == "docs"
Requires-Dist: myst-parser; extra == "docs"
Provides-Extra: gaming
Requires-Dist: pygame>=2.5.0; extra == "gaming"
Dynamic: author
Dynamic: home-page
Dynamic: license-file
Dynamic: requires-python
